<?xml version="1.0" encoding="UTF-8"?>
<topology>
   <networks>
      <network id="9">
         <routers>
            <router id="27">
               <ipv4Interfaces id="1">
                  <description>--- out of band mgmt ---</description>
                  <ipv4Address>
                     <ip>192.168.2.204</ip>
                     <prefixLength>24</prefixLength>
                  </ipv4Address>
                  <name>MgmtEth0/0/CPU0/0</name>
                  <shutdown>false</shutdown>
                  <type>CONFIGURED</type>
               </ipv4Interfaces>
               <ipv4Interfaces id="2">
                  <description>--- vers xrv2 Gi0/0/0/1 ---</description>
                  <ipv4Address>
                     <ip>192.168.4.4</ip>
                     <prefixLength>24</prefixLength>
                  </ipv4Address>
                  <name>GigabitEthernet0/0/0/0</name>
                  <shutdown>false</shutdown>
                  <type>CONFIGURED</type>
               </ipv4Interfaces>
               <ipv4Interfaces id="3">
                  <description>--- vers xrv3 Gi0/0/0/1 ---</description>
                  <ipv4Address>
                     <ip>192.168.3.4</ip>
                     <prefixLength>24</prefixLength>
                  </ipv4Address>
                  <name>GigabitEthernet0/0/0/1</name>
                  <shutdown>false</shutdown>
                  <type>CONFIGURED</type>
               </ipv4Interfaces>
               <ipv4Interfaces id="4">
                  <description>--- RID et inband mgmt ---</description>
                  <ipv4Address>
                     <ip>10.0.0.4</ip>
                     <prefixLength>32</prefixLength>
                  </ipv4Address>
                  <name>Loopback0</name>
                  <shutdown>false</shutdown>
                  <type>CONFIGURED</type>
               </ipv4Interfaces>
               <name>xrv4</name>
               <needTeRefresh>true</needTeRefresh>
               <routerId>
                  <areaId>0</areaId>
                  <autonomousSystem>65000</autonomousSystem>
                  <identifier>4444.4444.4444</identifier>
                  <lsIdentifier>0</lsIdentifier>
               </routerId>
               <virtual>false</virtual>
               <x>295</x>
               <y>42</y>
            </router>
            <router id="28">
               <ipv4Interfaces id="5">
                  <description>--- RID et inband mgmt ---</description>
                  <ipv4Address>
                     <ip>10.0.0.3</ip>
                     <prefixLength>32</prefixLength>
                  </ipv4Address>
                  <name>Loopback0</name>
                  <shutdown>false</shutdown>
                  <type>CONFIGURED</type>
               </ipv4Interfaces>
               <ipv4Interfaces id="6">
                  <description>test classement</description>
                  <ipv4Address>
                     <ip>1.1.1.1</ip>
                     <prefixLength>31</prefixLength>
                  </ipv4Address>
                  <name>GigabitEthernet0/0/0/0.10</name>
                  <shutdown>false</shutdown>
                  <type>CONFIGURED</type>
               </ipv4Interfaces>
               <ipv4Interfaces id="7">
                  <description>test classement</description>
                  <ipv4Address>
                     <ip>2.2.2.2</ip>
                     <prefixLength>31</prefixLength>
                  </ipv4Address>
                  <name>GigabitEthernet0/0/0/0.20</name>
                  <shutdown>false</shutdown>
                  <type>CONFIGURED</type>
               </ipv4Interfaces>
               <ipv4Interfaces id="8">
                  <description>test classement</description>
                  <ipv4Address>
                     <ip>4.4.4.4</ip>
                     <prefixLength>31</prefixLength>
                  </ipv4Address>
                  <name>GigabitEthernet0/0/0/0.200</name>
                  <shutdown>false</shutdown>
                  <type>CONFIGURED</type>
               </ipv4Interfaces>
               <ipv4Interfaces id="9">
                  <description>test classement</description>
                  <ipv4Address>
                     <ip>9.9.9.9</ip>
                     <prefixLength>31</prefixLength>
                  </ipv4Address>
                  <name>GigabitEthernet0/0/0/0.1020</name>
                  <shutdown>false</shutdown>
                  <type>CONFIGURED</type>
               </ipv4Interfaces>
               <ipv4Interfaces id="10">
                  <description>--- out of band mgmt ---</description>
                  <ipv4Address>
                     <ip>192.168.2.203</ip>
                     <prefixLength>24</prefixLength>
                  </ipv4Address>
                  <name>MgmtEth0/0/CPU0/0</name>
                  <shutdown>false</shutdown>
                  <type>CONFIGURED</type>
               </ipv4Interfaces>
               <ipv4Interfaces id="11">
                  <description>--- vers xrv1 Gi0/0/0/1 ---</description>
                  <ipv4Address>
                     <ip>192.168.20.3</ip>
                     <prefixLength>24</prefixLength>
                  </ipv4Address>
                  <name>GigabitEthernet0/0/0/0</name>
                  <shutdown>false</shutdown>
                  <type>CONFIGURED</type>
               </ipv4Interfaces>
               <ipv4Interfaces id="12">
                  <description>--- vers xrv4 Gi0/0/0/1 ---</description>
                  <ipv4Address>
                     <ip>192.168.3.3</ip>
                     <prefixLength>24</prefixLength>
                  </ipv4Address>
                  <name>GigabitEthernet0/0/0/1</name>
                  <shutdown>false</shutdown>
                  <type>CONFIGURED</type>
               </ipv4Interfaces>
               <name>xrv3</name>
               <needTeRefresh>true</needTeRefresh>
               <routerId>
                  <areaId>0</areaId>
                  <autonomousSystem>65000</autonomousSystem>
                  <identifier>3333.3333.3333</identifier>
                  <lsIdentifier>0</lsIdentifier>
               </routerId>
               <virtual>false</virtual>
               <x>487</x>
               <y>14</y>
            </router>
            <router id="29">
               <ipv4Interfaces id="13">
                  <description>--- out of band mgmt ---</description>
                  <ipv4Address>
                     <ip>192.168.2.202</ip>
                     <prefixLength>24</prefixLength>
                  </ipv4Address>
                  <name>MgmtEth0/0/CPU0/0</name>
                  <shutdown>false</shutdown>
                  <type>CONFIGURED</type>
               </ipv4Interfaces>
               <ipv4Interfaces id="14">
                  <description>--- vers xrv1 Gi0/0/0/0 ---</description>
                  <ipv4Address>
                     <ip>192.168.1.2</ip>
                     <prefixLength>24</prefixLength>
                  </ipv4Address>
                  <name>GigabitEthernet0/0/0/0</name>
                  <shutdown>false</shutdown>
                  <type>CONFIGURED</type>
               </ipv4Interfaces>
               <ipv4Interfaces id="15">
                  <description>--- vers xrv4 Gi0/0/0/0 ---</description>
                  <ipv4Address>
                     <ip>192.168.4.2</ip>
                     <prefixLength>24</prefixLength>
                  </ipv4Address>
                  <name>GigabitEthernet0/0/0/1</name>
                  <shutdown>false</shutdown>
                  <type>CONFIGURED</type>
               </ipv4Interfaces>
               <ipv4Interfaces id="16">
                  <description>--- RID et inband mgmt ---</description>
                  <ipv4Address>
                     <ip>10.0.0.2</ip>
                     <prefixLength>32</prefixLength>
                  </ipv4Address>
                  <name>Loopback0</name>
                  <shutdown>false</shutdown>
                  <type>CONFIGURED</type>
               </ipv4Interfaces>
               <ipv4Interfaces id="17">
                  <description>test plumber</description>
                  <ipv4Address>
                     <ip>169.255.255.4</ip>
                     <prefixLength>31</prefixLength>
                  </ipv4Address>
                  <name>GigabitEthernet0/0/0/0.1234</name>
                  <shutdown>false</shutdown>
                  <type>CONFIGURED</type>
               </ipv4Interfaces>
               <name>xrv2</name>
               <needTeRefresh>true</needTeRefresh>
               <routerId>
                  <areaId>0</areaId>
                  <autonomousSystem>65000</autonomousSystem>
                  <identifier>2222.2222.2222</identifier>
                  <lsIdentifier>0</lsIdentifier>
               </routerId>
               <virtual>false</virtual>
               <x>309</x>
               <y>148</y>
            </router>
            <router id="30">
               <ipv4Interfaces id="18">
                  <description></description>
                  <ipv4Address>
                     <ip>10.0.0.1</ip>
                     <prefixLength>32</prefixLength>
                  </ipv4Address>
                  <name>Loopback0</name>
                  <shutdown>false</shutdown>
                  <type>CONFIGURED</type>
               </ipv4Interfaces>
               <ipv4Interfaces id="19">
                  <description>--- to xrv2 ---</description>
                  <ipv4Address>
                     <ip>192.168.1.1</ip>
                     <prefixLength>24</prefixLength>
                  </ipv4Address>
                  <name>GigabitEthernet0/0/0/0</name>
                  <shutdown>false</shutdown>
                  <type>CONFIGURED</type>
               </ipv4Interfaces>
               <ipv4Interfaces id="20">
                  <description></description>
                  <ipv4Address>
                     <ip>192.168.20.1</ip>
                     <prefixLength>24</prefixLength>
                  </ipv4Address>
                  <name>GigabitEthernet0/0/0/1</name>
                  <shutdown>false</shutdown>
                  <type>CONFIGURED</type>
               </ipv4Interfaces>
               <ipv4Interfaces id="21">
                  <description></description>
                  <ipv4Address>
                     <ip>192.168.2.101</ip>
                     <prefixLength>24</prefixLength>
                  </ipv4Address>
                  <name>GigabitEthernet0/0/0/2</name>
                  <shutdown>false</shutdown>
                  <type>CONFIGURED</type>
               </ipv4Interfaces>
               <ipv4Interfaces id="22">
                  <description></description>
                  <ipv4Address>
                     <ip>192.168.100.101</ip>
                     <prefixLength>24</prefixLength>
                  </ipv4Address>
                  <name>MgmtEth0/0/CPU0/0</name>
                  <shutdown>false</shutdown>
                  <type>CONFIGURED</type>
               </ipv4Interfaces>
               <ipv4Interfaces id="23">
                  <description></description>
                  <ipv4Address>
                     <ip>192.168.200.1</ip>
                     <prefixLength>30</prefixLength>
                  </ipv4Address>
                  <name>tunnel-ip200</name>
                  <shutdown>false</shutdown>
                  <type>CONFIGURED</type>
               </ipv4Interfaces>
               <name>xrv1</name>
               <needTeRefresh>true</needTeRefresh>
               <routerId>
                  <areaId>0</areaId>
                  <autonomousSystem>65000</autonomousSystem>
                  <identifier>1111.1111.1111</identifier>
                  <lsIdentifier>0</lsIdentifier>
               </routerId>
               <virtual>false</virtual>
               <x>485</x>
               <y>127</y>
            </router>
            <router id="34">
               <needTeRefresh>true</needTeRefresh>
               <routerId>
                  <areaId>0</areaId>
                  <autonomousSystem>65000</autonomousSystem>
                  <identifier>0000.0000.0387</identifier>
                  <lsIdentifier>0</lsIdentifier>
               </routerId>
               <virtual>false</virtual>
               <x>18</x>
               <y>268</y>
            </router>
            <router id="39">
               <needTeRefresh>true</needTeRefresh>
               <routerId>
                  <areaId>0</areaId>
                  <autonomousSystem>65000</autonomousSystem>
                  <identifier>0000.0000.0382</identifier>
                  <lsIdentifier>0</lsIdentifier>
               </routerId>
               <virtual>false</virtual>
               <x>326</x>
               <y>637</y>
            </router>
            <router id="41">
               <needTeRefresh>true</needTeRefresh>
               <routerId>
                  <areaId>0</areaId>
                  <autonomousSystem>65000</autonomousSystem>
                  <identifier>0000.0000.0380</identifier>
                  <lsIdentifier>0</lsIdentifier>
               </routerId>
               <virtual>false</virtual>
               <x>76</x>
               <y>720</y>
            </router>
            <router id="43">
               <needTeRefresh>true</needTeRefresh>
               <routerId>
                  <areaId>0</areaId>
                  <autonomousSystem>65000</autonomousSystem>
                  <identifier>0000.0000.0378</identifier>
                  <lsIdentifier>0</lsIdentifier>
               </routerId>
               <virtual>false</virtual>
               <x>44</x>
               <y>353</y>
            </router>
            <router id="44">
               <needTeRefresh>true</needTeRefresh>
               <routerId>
                  <areaId>0</areaId>
                  <autonomousSystem>65000</autonomousSystem>
                  <identifier>0000.0000.0377</identifier>
                  <lsIdentifier>0</lsIdentifier>
               </routerId>
               <virtual>false</virtual>
               <x>129</x>
               <y>509</y>
            </router>
            <router id="45">
               <needTeRefresh>true</needTeRefresh>
               <routerId>
                  <areaId>0</areaId>
                  <autonomousSystem>65000</autonomousSystem>
                  <identifier>0000.0000.0376</identifier>
                  <lsIdentifier>0</lsIdentifier>
               </routerId>
               <virtual>false</virtual>
               <x>36</x>
               <y>498</y>
            </router>
            <router id="46">
               <needTeRefresh>true</needTeRefresh>
               <routerId>
                  <areaId>0</areaId>
                  <autonomousSystem>65000</autonomousSystem>
                  <identifier>0000.0000.0375</identifier>
                  <lsIdentifier>0</lsIdentifier>
               </routerId>
               <virtual>false</virtual>
               <x>98</x>
               <y>601</y>
            </router>
            <router id="53">
               <name>DIS</name>
               <needTeRefresh>true</needTeRefresh>
               <routerId>
                  <areaId>0</areaId>
                  <autonomousSystem>65000</autonomousSystem>
                  <identifier>0000.0000.0386-01</identifier>
                  <lsIdentifier>0</lsIdentifier>
               </routerId>
               <virtual>true</virtual>
               <x>0</x>
               <y>0</y>
            </router>
            <router id="54">
               <name>Unknown</name>
               <needTeRefresh>true</needTeRefresh>
               <routerId>
                  <areaId>0</areaId>
                  <autonomousSystem>65000</autonomousSystem>
                  <identifier>0000.0000.0385</identifier>
                  <lsIdentifier>0</lsIdentifier>
               </routerId>
               <virtual>false</virtual>
               <x>0</x>
               <y>0</y>
            </router>
            <router id="55">
               <needTeRefresh>true</needTeRefresh>
               <routerId>
                  <areaId>0</areaId>
                  <autonomousSystem>65000</autonomousSystem>
                  <identifier>0000.0000.0390</identifier>
                  <lsIdentifier>0</lsIdentifier>
               </routerId>
               <virtual>false</virtual>
               <x>0</x>
               <y>0</y>
            </router>
            <router id="56">
               <needTeRefresh>true</needTeRefresh>
               <routerId>
                  <areaId>0</areaId>
                  <autonomousSystem>65000</autonomousSystem>
                  <identifier>0000.0000.0379</identifier>
                  <lsIdentifier>0</lsIdentifier>
               </routerId>
               <virtual>false</virtual>
               <x>0</x>
               <y>0</y>
            </router>
            <router id="58">
               <needTeRefresh>true</needTeRefresh>
               <routerId>
                  <areaId>0</areaId>
                  <autonomousSystem>65000</autonomousSystem>
                  <identifier>0000.0000.0389</identifier>
                  <lsIdentifier>0</lsIdentifier>
               </routerId>
               <virtual>false</virtual>
               <x>0</x>
               <y>0</y>
            </router>
            <router id="59">
               <name>Unknown</name>
               <needTeRefresh>true</needTeRefresh>
               <routerId>
                  <areaId>0</areaId>
                  <autonomousSystem>65000</autonomousSystem>
                  <identifier>0000.0000.0381</identifier>
                  <lsIdentifier>0</lsIdentifier>
               </routerId>
               <virtual>false</virtual>
               <x>0</x>
               <y>0</y>
            </router>
            <router id="60">
               <name>Unknown</name>
               <needTeRefresh>true</needTeRefresh>
               <routerId>
                  <areaId>0</areaId>
                  <autonomousSystem>65000</autonomousSystem>
                  <identifier>0000.0000.0384</identifier>
                  <lsIdentifier>0</lsIdentifier>
               </routerId>
               <virtual>false</virtual>
               <x>0</x>
               <y>0</y>
            </router>
         </routers>
         <bgpAs>65000</bgpAs>
         <bgpPeer>
            <ip>192.168.2.101</ip>
            <prefixLength>32</prefixLength>
         </bgpPeer>
         <name>XRv HomeNet</name>
         <snmpCommunities>
            <snmpCommunity id="9">
               <community>BLT</community>
               <subnet>
                  <ip>10.0.0.0</ip>
                  <prefixLength>29</prefixLength>
               </subnet>
            </snmpCommunity>
            <snmpCommunity id="10">
               <community>BLT</community>
               <subnet>
                  <ip>169.254.0.0</ip>
                  <prefixLength>25</prefixLength>
               </subnet>
            </snmpCommunity>
         </snmpCommunities>
      </network>
   </networks>
   <users>
      <user id="1">
         <hashedPassword>51PYRYYR1/xUeA86NjYdNn0TuAHCD6+9</hashedPassword>
         <level>15</level>
         <name>admin</name>
         <remote>false</remote>
      </user>
   </users>
</topology>
